PyIRI/__init__.py
PyIRI/edp_update.py
PyIRI/igrf_library.py
PyIRI/main_library.py
PyIRI/plotting.py
PyIRI/sh_library.py
PyIRI/coefficients/Apex/Apex.nc
PyIRI/coefficients/CCIR/ccir11.asc
PyIRI/coefficients/CCIR/ccir12.asc
PyIRI/coefficients/CCIR/ccir13.asc
PyIRI/coefficients/CCIR/ccir14.asc
PyIRI/coefficients/CCIR/ccir15.asc
PyIRI/coefficients/CCIR/ccir16.asc
PyIRI/coefficients/CCIR/ccir17.asc
PyIRI/coefficients/CCIR/ccir18.asc
PyIRI/coefficients/CCIR/ccir19.asc
PyIRI/coefficients/CCIR/ccir20.asc
PyIRI/coefficients/CCIR/ccir21.asc
PyIRI/coefficients/CCIR/ccir22.asc
PyIRI/coefficients/Es/Es11.asc
PyIRI/coefficients/Es/Es12.asc
PyIRI/coefficients/Es/Es13.asc
PyIRI/coefficients/Es/Es14.asc
PyIRI/coefficients/Es/Es15.asc
PyIRI/coefficients/Es/Es16.asc
PyIRI/coefficients/Es/Es17.asc
PyIRI/coefficients/Es/Es18.asc
PyIRI/coefficients/Es/Es19.asc
PyIRI/coefficients/Es/Es20.asc
PyIRI/coefficients/Es/Es21.asc
PyIRI/coefficients/Es/Es22.asc
PyIRI/coefficients/Es/ymcoef.asc
PyIRI/coefficients/IGRF/IGRF13.shc
PyIRI/coefficients/IGRF/Inclination_IGRF_map.pdf
PyIRI/coefficients/SH/B0.nc
PyIRI/coefficients/SH/B1.nc
PyIRI/coefficients/SH/M3000F2.nc
PyIRI/coefficients/SH/foEs.nc
PyIRI/coefficients/SH/foF2_CCIR.nc
PyIRI/coefficients/SH/foF2_URSI.nc
PyIRI/coefficients/SH/hmF2_AMTB2013.nc
PyIRI/coefficients/SH/hmF2_SHU2015.nc
PyIRI/coefficients/URSI/ursi11.asc
PyIRI/coefficients/URSI/ursi12.asc
PyIRI/coefficients/URSI/ursi13.asc
PyIRI/coefficients/URSI/ursi14.asc
PyIRI/coefficients/URSI/ursi15.asc
PyIRI/coefficients/URSI/ursi16.asc
PyIRI/coefficients/URSI/ursi17.asc
PyIRI/coefficients/URSI/ursi18.asc
PyIRI/coefficients/URSI/ursi19.asc
PyIRI/coefficients/URSI/ursi20.asc
PyIRI/coefficients/URSI/ursi21.asc
PyIRI/coefficients/URSI/ursi22.asc
PyIRI/tests/__init__.py
PyIRI/tests/test_edp_update.py
PyIRI/tests/test_main_library.py
PyIRI/tests/test_regression_monthly_mean.py
PyIRI/tests/test_sh_library.py
pyiri-0.1.3.dist-info/licenses/LICENSE
pyiri-0.1.3.dist-info/METADATA
pyiri-0.1.3.dist-info/WHEEL
pyiri-0.1.3.dist-info/top_level.txt
pyiri-0.1.3.dist-info/RECORD
